LICENSE
MANIFEST.in
README.md
pyproject.toml
setup.cfg
setup.py
django_translation.egg-info/PKG-INFO
django_translation.egg-info/SOURCES.txt
django_translation.egg-info/dependency_links.txt
django_translation.egg-info/top_level.txt
templates/__init__.py
translation/__init__.py
translation/admin.py
translation/apps.py
translation/forms.py
translation/models.py
translation/serializers.py
translation/tests.py
translation/urls.py
translation/views.py
translation/migrations/__init__.py
translation/templates/__init__.py
translation/templates/translate.html
translation/templates/translation/translate.html
translation/templates/translation/partials/original_fields.html
translation/templates/translation/partials/translation_form.html
translation/templatetags/__init__.py
translation/templatetags/model_translation.py
translation/tests/0001_initial.py
translation/tests/__init__.py
translation/tests/models.py
translation/tests/test_forms.py
translation/tests/test_models.py
translation/tests/test_serializers.py
translation/tests/test_translations.py
translation/tests/test_urls.py
translation/tests/test_views_admin.py
translation/tests/test_views_api.py
translation/tests/migrations/__init__.py