Metadata-Version: 2.1
Name: django-translation
Version: 1.2
Summary: this is an application for model translation
Home-page: https://github.com/fritill-team/django_translation.git
Author: fritill
Author-email: mahmoud.nasser@fritill.com
License: MIT
Keywords: django translation custom
Platform: any
Classifier: Environment :: Web Environment
Classifier: Framework :: Django
Classifier: Intended Audience :: Developers
Classifier: License :: OSI Approved :: BSD License
Classifier: Operating System :: OS Independent
Classifier: Programming Language :: Python
Classifier: Programming Language :: Python :: 3
Classifier: Programming Language :: Python :: 3 :: Only
Classifier: Programming Language :: Python :: 3.8
Classifier: Programming Language :: Python :: 3.9
Classifier: Topic :: Internet :: WWW/HTTP
Classifier: Topic :: Internet :: WWW/HTTP :: Dynamic Content
License-File: LICENSE
